deklinacija/__init__.py
deklinacija/main.py
deklinacija/utils.py
deklinacija/vokativ_database.csv
deklinacija-1.7.1.dist-info/METADATA
deklinacija-1.7.1.dist-info/WHEEL
deklinacija-1.7.1.dist-info/licenses/LICENSE
deklinacija-1.7.1.dist-info/RECORD
