Metadata-Version: 2.1
Name: deklinacija
Version: 1.7.1
Summary: A Python library for declension of personal names in Serbian
Project-URL: Homepage, https://github.com/urelja/deklinacija
Project-URL: Bug Tracker, https://github.com/urelja/deklinacija/issues
Author-email: urelja <code.relja@gmail.com>
License-File: LICENSE
Classifier: License :: OSI Approved :: MIT License
Classifier: Operating System :: OS Independent
Classifier: Programming Language :: Python :: 3
Requires-Python: >=3.7
